pycaleva/__init__.py
pycaleva/_basecalib.py
pycaleva/_report.py
pycaleva/_result_types.py
pycaleva/calbelt.py
pycaleva/calibeval.py
pycaleva/metrics.py
pycaleva-0.8.2.dist-info/LICENSE
pycaleva-0.8.2.dist-info/METADATA
pycaleva-0.8.2.dist-info/WHEEL
pycaleva-0.8.2.dist-info/top_level.txt
pycaleva-0.8.2.dist-info/RECORD
