Metadata-Version: 2.1
Name: pycaleva
Version: 0.8.2
Summary: A framework for calibration evaluation of binary classification models
Home-page: https://github.com/MartinWeigl/pycaleva
Author: Martin Weigl
Author-email: martinweigl48@gmail.com
License: UNKNOWN
Project-URL: Source, https://github.com/MartinWeigl/pycaleva
Project-URL: Documentation, https://martinweigl.github.io/pycaleva/
Keywords: calibration,classification,model,machine_learning,statistics
Platform: UNKNOWN
Classifier: Programming Language :: Python :: 3 :: Only
Classifier: License :: OSI Approved :: BSD License
Classifier: Operating System :: OS Independent
Classifier: Development Status :: 5 - Production/Stable
Classifier: Topic :: Scientific/Engineering :: Artificial Intelligence
License-File: LICENSE
Requires-Dist: fpdf2 >=2.7
Requires-Dist: ipython >=8.24
Requires-Dist: matplotlib >=3.8
Requires-Dist: numpy >=1.26
Requires-Dist: pandas >=2.2
Requires-Dist: scikit-learn >=1.4
Requires-Dist: scipy >=1.13
Requires-Dist: statsmodels >=0.14
Requires-Dist: tqdm >=4.66
